CHANGELOG.txt
LICENSE.txt
MANIFEST.in
READMME.txt
setup.py
basiccalculator/__init__.py
twodigitcalculator.egg-info/PKG-INFO
twodigitcalculator.egg-info/SOURCES.txt
twodigitcalculator.egg-info/dependency_links.txt
twodigitcalculator.egg-info/top_level.txt