Metadata-Version: 2.1
Name: twodigitcalculator
Version: 0.0.1
Summary: A two digit calculator with basic operations
Home-page: 
Author: Sandeep Chowdhury
Author-email: sandeepiit.ism@gmail.com
License: MIT
Keywords: calculator
Classifier: Development Status :: 5 - Production/Stable
Classifier: Intended Audience :: Education
Classifier: Operating System :: Microsoft :: Windows :: Windows 10
Classifier: License :: OSI Approved :: MIT License
Classifier: Programming Language :: Python :: 3
License-File: LICENSE.txt
